MANIFEST.in
README.org
setup.py
demo/__init__.py
demo/local_settings.py
demo/settings.py
demo/urls.py
demo/views.py
demo/wsgi.py
django_tlsauth/__init__.py
django_tlsauth/forms.py
django_tlsauth/urls.py
django_tlsauth/views.py
django_tlsauth.egg-info/PKG-INFO
django_tlsauth.egg-info/SOURCES.txt
django_tlsauth.egg-info/dependency_links.txt
django_tlsauth.egg-info/requires.txt
django_tlsauth.egg-info/top_level.txt