Metadata-Version: 1.1
Name: django-tlsauth
Version: 0.1.2
Summary: Django app implementing TLS Authentication - simple client certificate CA inclusive
Home-page: http://packages.python.org/django_tlsauth
Author: Stefan Marsiske
Author-email: s@ctrlc.hu
License: BSD
Keywords: django crypto authentication TLS certificate x509 CA
Platform: UNKNOWN
Classifier: Development Status :: 4 - Beta
Classifier: License :: OSI Approved :: BSD License
Classifier: Topic :: Security :: Cryptography
Classifier: Environment :: Web Environment
